LICENSE
MANIFEST.in
README.md
setup.cfg
setup.py
versioneer.py
pisa/README.md
pisa/__init__.py
pisa/_version.py
pisa/general_conventions.md
pisa/glossary.md
pisa/units_and_uncertainties.md
pisa.egg-info/PKG-INFO
pisa.egg-info/SOURCES.txt
pisa.egg-info/dependency_links.txt
pisa.egg-info/entry_points.txt
pisa.egg-info/not-zip-safe
pisa.egg-info/requires.txt
pisa.egg-info/top_level.txt
pisa/analysis/README.md
pisa/analysis/__init__.py
pisa/analysis/analysis.py
pisa/core/README.md
pisa/core/__init__.py
pisa/core/bin_indexing.py
pisa/core/binning.py
pisa/core/container.py
pisa/core/detectors.py
pisa/core/distribution_maker.py
pisa/core/events.py
pisa/core/events_pi.py
pisa/core/map.py
pisa/core/param.py
pisa/core/pipeline.py
pisa/core/prior.py
pisa/core/stage.py
pisa/core/translation.py
pisa/scripts/README.md
pisa/scripts/__init__.py
pisa/scripts/add_flux_to_events_file.py
pisa/scripts/compare.py
pisa/scripts/convert_config_format.py
pisa/scripts/create_barr_sys_tables_mceq.py
pisa/scripts/fit_hypersurfaces.py
pisa/scripts/make_events_file.py
pisa/scripts/make_nufit_theta23_spline_priors.py
pisa/scripts/test_flux_weights.py
pisa/stages/GLOBALS.md
pisa/stages/README.md
pisa/stages/__init__.py
pisa/stages/how_to_service.md
pisa/stages/absorption/__init__.py
pisa/stages/absorption/earth_absorption.py
pisa/stages/aeff/README.md
pisa/stages/aeff/__init__.py
pisa/stages/aeff/aeff.py
pisa/stages/aeff/param.py
pisa/stages/aeff/weight.py
pisa/stages/aeff/weight_hnl.py
pisa/stages/background/__init__.py
pisa/stages/background/atm_muons.py
pisa/stages/data/README.md
pisa/stages/data/__init__.py
pisa/stages/data/csv_data_hist.py
pisa/stages/data/csv_icc_hist.py
pisa/stages/data/csv_loader.py
pisa/stages/data/grid.py
pisa/stages/data/licloader_weighter.py
pisa/stages/data/meows_loader.py
pisa/stages/data/simple_data_loader.py
pisa/stages/data/simple_signal.py
pisa/stages/data/sqlite_loader.py
pisa/stages/data/toy_event_generator.py
pisa/stages/discr_sys/README.md
pisa/stages/discr_sys/__init__.py
pisa/stages/discr_sys/hypersurfaces.py
pisa/stages/discr_sys/ultrasurfaces.py
pisa/stages/flux/README.md
pisa/stages/flux/__init__.py
pisa/stages/flux/airs.py
