Metadata-Version: 2.1
Name: pisa
Version: 4.2
Summary: Tools for analyzing and drawing statistical conclusions from experimental data
Home-page: http://github.com/icecubeopensource/pisa
Author: The IceCube Collaboration
Author-email: analysis@icecube.wisc.edu
License: Apache 2.0
Platform: UNKNOWN
Requires-Python: >=3.6
Provides-Extra: develop
License-File: LICENSE
